{
  "Rosmontis:RelicID": {
    "NAME": "Good Relic",
    "FLAVOR": "Flavor text displayed in detailed relic view.",
    "DESCRIPTIONS": [
      "Gain [E] at the start of your turn. [E] is an energy icon."
    ]
  },
  "Rosmontis:AnnE": {
    "NAME": "歼灭战装备",
    "FLAVOR": "迷迭香持有这些重剑，只有她能使用的剑",
    "DESCRIPTIONS": [
      "当你使用攻击牌时，对所有敌人造成3点伤害"
    ]
  },"Rosmontis:StolenMiniCake": {
  "NAME": "Good Relic",
  "FLAVOR": "Flavor text displayed in detailed relic view.",
  "DESCRIPTIONS": [
    "Gain [E] at the start of your turn. [E] is an energy icon."
  ]
  },
  "Rosmontis:ShoesFromAmiya": {
    "NAME": "ShoesFromAmiya",
    "FLAVOR": "Flavor text displayed in detailed relic view.",
    "DESCRIPTIONS": [
      "Gain [E] at the start of your turn. [E] is an energy icon."
    ]
  },
  "Rosmontis:Terminal": {
    "NAME": "Terminal",
    "FLAVOR": "Flavor text displayed in detailed relic view.",
    "DESCRIPTIONS": [
      "Gain [E] at the start of your turn. [E] is an energy icon."
    ]
  },
  "Rosmontis:Plant": {
    "NAME": "Plant",
    "FLAVOR": "Flavor text displayed in detailed relic view.",
    "DESCRIPTIONS": [
      "Gain [E] at the start of your turn. [E] is an energy icon."
    ]
  },
  "Rosmontis:JudgeCount": {
    "NAME": "JudgeCount",
    "FLAVOR": "Flavor text displayed in detailed relic view.",
    "DESCRIPTIONS": [
      "Gain [E] at the start of your turn. [E] is an energy icon."
    ]
  }
}