{
  "${modID}:EventID": {
    "NAME": "Event Name",
    "DESCRIPTIONS": [
      "This is event text, generally used to describe what's happening.",
      "#g~This~ #g~text~ #g~is~ #g~green~ #g~and~ #g~wavy.~",
      "#r@RED@ #r@AND@ #r@VIBRATING@ #r@TEXT.@",
      "#rRed #gGreen #yYellow #bBlue #pPurple. ~Wavy~ @vibrating.@",
      "You have to mark every word individually.",
      "You can also use [#ffffff]white[] hex color codes like this to color text.",
      "This also works in card text! But not on keywords."
    ],
    "OPTIONS": [
      "[Action Description] What you actually get.",
      "[Denial] #rLose #r1 #rMax #rHP. Bad stuff is red.",
      "[Acceptance] #gGain #gApotheosis. Good stuff is green.",
      "[Leave]",
      "Select card to remove. (You can also stick extra text like this in here.)"
    ]
  },
  "${modID}:PickUp": {
    "NAME": "拾遗",
    "DESCRIPTIONS": [
      "你恍然发现自己似乎回到了罗德岛的廊桥上。低头发现了 #y一个钱包。",
      "你在原处等了一小会，远远看到一个菲林赶来。",
      "你捡起了钱包，隔着皮革就能感受到里面沉甸甸的钱，还是快点离开吧。",
      "一个钱包明晃晃在地上？太可疑了，还是当作没看见好。",
      "杰西卡对你表示感谢，邀请你共进下午茶。",
      "你与杰西卡一同品鉴了她的豪华下午茶，美味。（回复了全部生命值,增加了15生命上限）",
      "你拒绝了邀请，还有更重要的事在眼前。临走时，她将一份博士的礼物转交给你。"
    ],
    "OPTIONS": [
      "要不等等人吧。",
      "四下无人，捡走吧。",
      "还是不要多管了。",
      "欣然接受。",
      "礼貌拒绝并离开。",
      "好像是杰西卡。",
      "[离开]"
    ]
  },
  "${modID}:RhodesIslandSafeHouse": {
    "NAME": "罗德岛安全屋",
    "DESCRIPTIONS": [
      "转过拐角，你面前出现一闪熟悉的门。门后似乎是罗德岛各地常见的备用安全屋，要去看看吗？",
      "你使用终端解锁了安全屋，里面虽然略显简陋，但基础功能一应俱全，可以供临时歇脚。",
      "你尝试强行破开了安全屋，不小心被锋利的铁片划伤手臂。安全屋内虽然略显简陋，但基础功能一应俱全，可以供临时歇脚。",
      "还是赶路要紧，溜了溜了。",
      "你使用了墙上的医疗箱，躺在床上休息了一会。感觉好多了，是时候离开了。",
      "你在屋内搜刮看一番，找到了一个 #y遗物 ！是时候该离开了。",
      "你使用屋内遗留的工具升级了你的装备，是时候该离开了了。"
    ],
    "OPTIONS": [
      "使用终端解锁。",
      "[需要遗物：迷迭香的终端]",
      "[失去20生命] 暴力破开。",
      "[离开]",
      "回复最大生命上限的50%。",
      "获得2件 #y遗物 。",
      "选择升级一张卡，再随机升级两张卡。",
      ""
    ]
  }
}
